pantheon/__init__.py
pantheon/pantheon.py
pantheon/RateLimit/RateLimiter.py
pantheon/RateLimit/RateLimiterManager.py
pantheon/RateLimit/__init__.py
pantheon/utils/__init__.py
pantheon/utils/exceptions.py
pantheon/utils/utils.py
test/__init__.py
test/config.py
test/test_accounts.py
test/test_champion.py
test/test_champion_mastery.py
test/test_clash.py
test/test_league.py
test/test_lor.py
test/test_match.py
test/test_pantheon.py
test/test_spectator.py
test/test_status.py
test/test_summoner.py
test/test_tft_league.py
test/test_tft_match.py
test/test_tft_summoner.py
test/test_third_party_code.py
test/test_tournament.py
test/test_valorant.py
pantheon-2.0.0.dist-info/METADATA
pantheon-2.0.0.dist-info/WHEEL
pantheon-2.0.0.dist-info/top_level.txt
pantheon-2.0.0.dist-info/RECORD
