Metadata-Version: 2.1
Name: pantheon
Version: 2.0.0
Summary: Riot API library for Python and asyncio
Home-page: https://github.com/Canisback/pantheon
Author: Canisback
Author-email: canisback@gmail.com
License: UNKNOWN
Keywords: Riot API,python
Platform: UNKNOWN
Requires-Dist: aiohttp
Requires-Dist: certifi
